{
	"debugger":true,
	"driver_manager_log":false,
	"options":[{
		"action_all_count":0,
		"action_err_count":0,
		"action_succ_count":0,
		"debugger":true,
		"domino_after_prepared_driver":"com.lwjhn.domino2sql.driver.AfterPrepareDocument",
		"domino_error_flag_field":"ArcXC_Error_FLAG",
		"domino_prepared_sqlquery_driver":"com.rjsoft.prepared.PrepareSqlQueryRJDoc",
		"domino_process_statement_driver":"com.rjsoft.prepared.ProcessStatementRJDocNoCache",
		"domino_queries":[{
			"action_all_count":8,
			"action_err_count":0,
			"action_succ_count":8,
			"debugger":true,
			"domino_dbpath":"egov/dispatch.nsf",
			"domino_error_flag_field":"ArcXC_Error_FLAG",
			"domino_query":"Form=\"FlowForm\" & MSSDATABASE!=\"\" & DraftDate > [2020-07-20] & DraftDate < [2020-07-25]",
			"domino_server":"OA/SRV/FJSF",
			"domino_succ_flag_field":"ArcXC_Succ_FLAG",
			"domino_uuid_prefix":"ArcXC_UUID_",
			"enable":true,
			"error_continue":true,
			"ftppath":"/FTP_XC/",
			"ftppath_regex":"^[a-zA-Z]:",
			"update_mode_no_insert":true,
			"vesion":"1.6.7"
		}],
		"domino_query":"Form=\"FlowForm\" & MSSDATABASE!=\"\" & DraftDate > [2020-07-20] & DraftDate < [2020-07-25]",
		"domino_server":"OA/SRV/FJSF",
		"domino_succ_flag_field":"ArcXC_Succ_FLAG",
		"domino_uuid_prefix":"ArcXC_UUID_",
		"enable":true,
		"error_continue":true,
		"extended_options":{
			"sql_field_attachment":{
				"jdbc_type":"VARCHAR",
				"sql_name":"JSONATT",
				"scale_length":0
			},
			"export_processing":true,
			"export_flow":true,
			"export_opinion":true
		},
		"ftppath":"/FTP_XC/",
		"ftppath_regex":"^[a-zA-Z]:",
		"sql_field_others":[{
			"date_format":"yyyy-MM-dd HH:mm:ss",
			"domino_name":"ArcXC_UUID_16",
			"jdbc_type":"VARCHAR",
			"join_delimiter":"; ",
			"scale_length":0,
			"sql_name":"ID"
		},{
			"date_format":"yyyy-MM-dd HH:mm:ss",
			"domino_formula":"@Text(@DocumentUniqueID)",
			"jdbc_type":"VARCHAR",
			"join_delimiter":"; ",
			"scale_length":0,
			"sql_name":"DOMINOID"
		},{
			"date_format":"yyyy-MM-dd HH:mm:ss",
			"domino_name":"Subject",
			"jdbc_type":"VARCHAR",
			"join_delimiter":"; ",
			"scale_length":0,
			"sql_name":"Subject"
		},{
			"date_format":"yyyy-MM-dd HH:mm:ss",
			"domino_name":"DocWord",
			"jdbc_type":"VARCHAR",
			"join_delimiter":"; ",
			"scale_length":0,
			"sql_name":"DocWord"
		},{
			"date_format":"yyyy-MM-dd HH:mm:ss",
			"domino_name":"DocType",
			"jdbc_type":"VARCHAR",
			"join_delimiter":"; ",
			"scale_length":0,
			"sql_name":"DocType"
		},{
			"date_format":"yyyy-MM-dd HH:mm:ss",
			"domino_name":"UrgentLevel",
			"jdbc_type":"VARCHAR",
			"join_delimiter":"; ",
			"scale_length":0,
			"sql_name":"UrgentLevel"
		},{
			"date_format":"yyyy-MM-dd HH:mm:ss",
			"domino_name":"DraftDept",
			"jdbc_type":"VARCHAR",
			"join_delimiter":"; ",
			"scale_length":0,
			"sql_name":"DraftDept"
		},{
			"date_format":"yyyy-MM-dd HH:mm:ss",
			"domino_name":"SecLevel",
			"jdbc_type":"VARCHAR",
			"join_delimiter":"; ",
			"scale_length":0,
			"sql_name":"SecLevel"
		},{
			"date_format":"yyyy-MM-dd HH:mm:ss",
			"domino_name":"FileType",
			"jdbc_type":"VARCHAR",
			"join_delimiter":"; ",
			"scale_length":0,
			"sql_name":"FileType"
		},{
			"date_format":"yyyy-MM-dd HH:mm:ss",
			"domino_name":"IsPublic",
			"jdbc_type":"VARCHAR",
			"join_delimiter":"; ",
			"scale_length":0,
			"sql_name":"IsPublic"
		},{
			"date_format":"yyyy-MM-dd HH:mm:ss",
			"domino_name":"MainSend",
			"jdbc_type":"VARCHAR",
			"join_delimiter":"; ",
			"scale_length":0,
			"sql_name":"MainSend"
		},{
			"date_format":"yyyy-MM-dd HH:mm:ss",
			"domino_name":"CopySend",
			"jdbc_type":"VARCHAR",
			"join_delimiter":"; ",
			"scale_length":0,
			"sql_name":"CopySend"
		},{
			"date_format":"yyyy-MM-dd HH:mm:ss",
			"domino_name":"PrintTerm",
			"jdbc_type":"VARCHAR",
			"join_delimiter":"; ",
			"scale_length":0,
			"sql_name":"PrintTerm"
		},{
			"date_format":"yyyy-MM-dd HH:mm:ss",
			"domino_name":"Remark",
			"jdbc_type":"VARCHAR",
			"join_delimiter":"; ",
			"scale_length":0,
			"sql_name":"Remark"
		},{
			"date_format":"yyyy-MM-dd HH:mm:ss",
			"domino_formula":"temp:=SignDate;temp:=@If(@IsTime(temp);temp;@TextToTime(@ReplaceSubstring(temp;\"年\":\"月\":\"日\";\"-\":\"-\":\"\")));@if(@IsError(temp) | @IsNull(temp);@Nothing;temp);",
			"jdbc_type":"TIMESTAMP",
			"join_delimiter":"; ",
			"scale_length":0,
			"sql_name":"SignDateTime"
		},{
			"date_format":"yyyy-MM-dd HH:mm:ss",
			"domino_name":"DraftDate",
			"jdbc_type":"TIMESTAMP",
			"join_delimiter":"; ",
			"scale_length":0,
			"sql_name":"DraftDate"
		},{
			"date_format":"yyyy-MM-dd HH:mm:ss",
			"domino_formula":"1",
			"jdbc_type":"INTEGER",
			"join_delimiter":"; ",
			"scale_length":0,
			"sql_name":"PrintNum"
		},{
			"date_format":"yyyy-MM-dd HH:mm:ss",
			"domino_formula":"@Nothing",
			"jdbc_type":"VARCHAR",
			"join_delimiter":"; ",
			"scale_length":0,
			"sql_name":"OTHER"
		}],
		"sql_table":"XC_DEMO.EGOV_DISPATCH_HISTORY",
		"update_mode_no_insert":true,
		"vesion":"1.6.7"
	}],
	"sql_driver":"com.mysql.cj.jdbc.Driver",
	"sql_password":"abcd1234",
	"sql_url":"jdbc:mysql://192.168.210.153:3399?connectTimeout=3000&socketTimeout=60000&useUnicode=true&characterEncoding=UTF-8&serverTimezone=UTC",
	"sql_username":"rjsoft"
}